Workbook

Sheet 2026
A4: PERÍODO DE APURAÇÃO: 2026 | G4: =A4 -> PERÍODO DE APURAÇÃO: 2026 | N4: =G4 -> PERÍODO DE APURAÇÃO: 2026
A5: INVESTIDOR: | G5: =A5 -> INVESTIDOR: | N5: =G5 -> INVESTIDOR:
A6: CPF: | G6: =A6 -> CPF: | N6: =G6 -> CPF:
A8: APURAÇÃO B3 | G8: CONTROLE DE ATIVOS | N8: CONTROLE DE ATIVOS
B10: RESULTADOS EM DAY TRADE (ANUAL) | H10: ATIVOS EM CARTEIRA | P10: DERIVATIVOS EM CARTEIRA
B11: MÊS | C11: PREJUÍZO | D11: LUCRO | E11: SALDO ACUM. | H11: PAPEL | I11: QUANTIDADE | J11: PREÇO MÉDIO | K11: CUSTO TOTAL | L11: RENDIMENTO | P11: VARIÁVEL | Q11: PRÊMIO | R11: TARIFA | S11: VENCIMENTO
B12: PREJUÍZOS ACUMULADOS: | E12: 0
B13: 46023 | C13: =IFERROR(MIN(0,'01.26'!$C$15),0) -> 0 | D13: =IFERROR(MAX(0,'01.26'!$C$15),0) -> 0 | E13: =E12+C13+D13 -> 0
B14: 46054 | C14: =IFERROR(MIN(0,'02.26'!$C$15),0) -> 0 | D14: =IFERROR(MAX(0,'02.26'!$C$15),0) -> 0 | E14: =E13+C14+D14 -> 0
B15: 46082 | C15: =IFERROR(MIN(0,'03.26'!$C$15),0) -> 0 | D15: =IFERROR(MAX(0,'03.26'!$C$15),0) -> 0 | E15: =E14+C15+D15 -> 0
B16: 46113 | C16: =IFERROR(MIN(0,'04.26'!$C$15),0) -> 0 | D16: =IFERROR(MAX(0,'04.26'!$C$15),0) -> 0 | E16: =E15+C16+D16 -> 0
B17: 46143 | C17: =IFERROR(MIN(0,'05.26'!$C$15),0) -> 0 | D17: =IFERROR(MAX(0,'05.26'!$C$15),0) -> 0 | E17: =E16+C17+D17 -> 0
B18: 46174 | C18: =IFERROR(MIN(0,'06.26'!$C$15),0) -> 0 | D18: =IFERROR(MAX(0,'06.26'!$C$15),0) -> 0 | E18: =E17+C18+D18 -> 0
B19: 46204 | C19: =IFERROR(MIN(0,'07.26'!$C$15),0) -> 0 | D19: =IFERROR(MAX(0,'07.26'!$C$15),0) -> 0 | E19: =E18+C19+D19 -> 0
B20: 46235 | C20: =IFERROR(MIN(0,'08.26'!$C$15),0) -> 0 | D20: =IFERROR(MAX(0,'08.26'!$C$15),0) -> 0 | E20: =E19+C20+D20 -> 0
B21: 46266 | C21: =IFERROR(MIN(0,'09.26'!$C$15),0) -> 0 | D21: =IFERROR(MAX(0,'09.26'!$C$15),0) -> 0 | E21: =E20+C21+D21 -> 0
B22: 46296 | C22: =IFERROR(MIN(0,'10.26'!$C$15),0) -> 0 | D22: =IFERROR(MAX(0,'10.26'!$C$15),0) -> 0 | E22: =E21+C22+D22 -> 0
B23: 46327 | C23: =IFERROR(MIN(0,'11.26'!$C$15),0) -> 0 | D23: =IFERROR(MAX(0,'11.26'!$C$15),0) -> 0 | E23: =E22+C23+D23 -> 0
B24: 46357 | C24: =IFERROR(MIN(0,'12.26'!$C$15),0) -> 0 | D24: =IFERROR(MAX(0,'12.26'!$C$15),0) -> 0 | E24: =E23+C24+D24 -> 0
B30: RESULTADOS EM SWING TRADE (ANUAL) | N30: CONTROLE DE ATIVOS
B31: MÊS | C31: PREJUÍZO | D31: LUCRO | E31: SALDO ACUM.
B32: PREJUÍZOS ACUMULADOS: | E32: 0
B33: 46023 | C33: =IFERROR(MIN(0,'01.26'!$B$15),0) -> 0 | D33: =IFERROR(MAX(0,'01.26'!$B$15),0) -> 0 | E33: =E32+C33+D33 -> 0 | O33: OPÇÕES DE MERCADO FUTURO
B34: 46054 | C34: =IFERROR(MIN(0,'02.26'!$B$15),0) -> 0 | D34: =IFERROR(MAX(0,'02.26'!$B$15),0) -> 0 | E34: =E33+C34+D34 -> 0 | O34: OPERAÇÃO | Q34: ATIVO | R34: QUANTIDADE | S34: VALOR | T34: VENCIMENTO
B35: 46082 | C35: =IFERROR(MIN(0,'03.26'!$B$15),0) -> 0 | D35: =IFERROR(MAX(0,'03.26'!$B$15),0) -> 0 | E35: =E34+C35+D35 -> 0
B36: 46113 | C36: =IFERROR(MIN(0,'04.26'!$B$15),0) -> 0 | D36: =IFERROR(MAX(0,'04.26'!$B$15),0) -> 0 | E36: =E35+C36+D36 -> 0
B37: 46143 | C37: =IFERROR(MIN(0,'05.26'!$B$15),0) -> 0 | D37: =IFERROR(MAX(0,'05.26'!$B$15),0) -> 0 | E37: =E36+C37+D37 -> 0
B38: 46174 | C38: =IFERROR(MIN(0,'06.26'!$B$15),0) -> 0 | D38: =IFERROR(MAX(0,'06.26'!$B$15),0) -> 0 | E38: =E37+C38+D38 -> 0
B39: 46204 | C39: =IFERROR(MIN(0,'07.26'!$B$15),0) -> 0 | D39: =IFERROR(MAX(0,'07.26'!$B$15),0) -> 0 | E39: =E38+C39+D39 -> 0
B40: 46235 | C40: =IFERROR(MIN(0,'08.26'!$B$15),0) -> 0 | D40: =IFERROR(MAX(0,'08.26'!$B$15),0) -> 0 | E40: =E39+C40+D40 -> 0
B41: 46266 | C41: =IFERROR(MIN(0,'09.26'!$B$15),0) -> 0 | D41: =IFERROR(MAX(0,'09.26'!$B$15),0) -> 0 | E41: =E40+C41+D41 -> 0
B42: 46296 | C42: =IFERROR(MIN(0,'10.26'!$B$15),0) -> 0 | D42: =IFERROR(MAX(0,'10.26'!$B$15),0) -> 0 | E42: =E41+C42+D42 -> 0
B43: 46327 | C43: =IFERROR(MIN(0,'11.26'!$B$15),0) -> 0 | D43: =IFERROR(MAX(0,'11.26'!$B$15),0) -> 0 | E43: =E42+C43+D43 -> 0
B44: 46357 | C44: =IFERROR(MIN(0,'12.26'!$B$15),0) -> 0 | D44: =IFERROR(MAX(0,'12.26'!$B$15),0) -> 0 | E44: =E43+C44+D44 -> 0 | H44: VALOR TOTAL DE PATRIMÔNIO ACUMULADO: | K44: =SUM(K12:K38) -> 0
A53: =A4 -> PERÍODO DE APURAÇÃO: 2026 | G53: =A4 -> PERÍODO DE APURAÇÃO: 2026 | N53: =G53 -> PERÍODO DE APURAÇÃO: 2026
A54: =A5 -> INVESTIDOR: | G54: =A54 -> INVESTIDOR: | N54: =G54 -> INVESTIDOR:
A55: =A6 -> CPF: | G55: =A55 -> CPF: | N55: =G55 -> CPF:
A57: APURAÇÃO B3 | G57: POSIÇÃO DA CARTEIRA POR ATIVO (MENSAL) | N57: EVOLUÇÃO PATRIMONIAL (ANUAL)
B59: RESULTADOS EM FUNDOS IMOBILIÁRIOS (ANUAL)
B60: MÊS | C60: PREJUÍZO | D60: LUCRO | E60: SALDO ACUM.
B61: PREJUÍZOS ACUMULADOS:2025 | E61: 0
B62: 46023 | C62: =IFERROR(MIN(0,'01.26'!$B$49),0) -> 0 | D62: =IFERROR(MAX(0,'01.26'!$B$49),0) -> 0 | E62: =E61+C62+D62 -> 0
B63: 46054 | C63: =IFERROR(MIN(0,'02.26'!$B$49),0) -> 0 | D63: =IFERROR(MAX(0,'02.26'!$B$49),0) -> 0 | E63: =E62+C63+D63 -> 0
B64: 46082 | C64: =IFERROR(MIN(0,'03.26'!$B$49),0) -> 0 | D64: =IFERROR(MAX(0,'03.26'!$B$49),0) -> 0 | E64: =E63+C64+D64 -> 0
B65: 46113 | C65: =IFERROR(MIN(0,'04.26'!$B$49),0) -> 0 | D65: =IFERROR(MAX(0,'04.26'!$B$49),0) -> 0 | E65: =E64+C65+D65 -> 0
B66: 46143 | C66: =IFERROR(MIN(0,'05.26'!$B$49),0) -> 0 | D66: =IFERROR(MAX(0,'05.26'!$B$49),0) -> 0 | E66: =E65+C66+D66 -> 0
B67: 46174 | C67: =IFERROR(MIN(0,'06.26'!$B$49),0) -> 0 | D67: =IFERROR(MAX(0,'06.26'!$B$49),0) -> 0 | E67: =E66+C67+D67 -> 0
B68: 46204 | C68: =IFERROR(MIN(0,'07.26'!$B$49),0) -> 0 | D68: =IFERROR(MAX(0,'07.26'!$B$49),0) -> 0 | E68: =E67+C68+D68 -> 0
B69: 46235 | C69: =IFERROR(MIN(0,'08.26'!$B$49),0) -> 0 | D69: =IFERROR(MAX(0,'08.26'!$B$49),0) -> 0 | E69: =E68+C69+D69 -> 0
B70: 46266 | C70: =IFERROR(MIN(0,'09.26'!$B$49),0) -> 0 | D70: =IFERROR(MAX(0,'09.26'!$B$49),0) -> 0 | E70: =E69+C70+D70 -> 0
B71: 46296 | C71: =IFERROR(MIN(0,'10.26'!$B$49),0) -> 0 | D71: =IFERROR(MAX(0,'10.26'!$B$49),0) -> 0 | E71: =E70+C71+D71 -> 0
B72: 46327 | C72: =IFERROR(MIN(0,'11.26'!$B$49),0) -> 0 | D72: =IFERROR(MAX(0,'11.26'!$B$49),0) -> 0 | E72: =E71+C72+D72 -> 0
B73: 46357 | C73: =IFERROR(MIN(0,'12.26'!$B$49),0) -> 0 | D73: =IFERROR(MAX(0,'12.26'!$B$49),0) -> 0 | E73: =E72+C73+D73 -> 0
A102: =A53 -> PERÍODO DE APURAÇÃO: 2026
A103: =A54 -> INVESTIDOR:
A104: =A55 -> CPF:
A106: RESULTADO ANUAL
B108: COMPENSAÇÃO DE IR. RETIDO NA FONTE EM D.T. / S.T.
B109: MÊS | C109: IR. RETIDO NO MÊS | D109: IR. COMPENSADO | E109: ACUMULADO
B110: 46023 | C110: =IFERROR('01.26'!$C$36+'01.26'!$C$39,0) -> 0 | D110: =IFERROR(MAX(0,'01.26'!$C$35-'01.26'!$C$42),0) -> 0 | E110: =C110-D110 -> 0
B111: 46054 | C111: =IFERROR('02.26'!$C$36+'02.26'!$C$39,0) -> 0 | D111: =IFERROR(MAX(0,'02.26'!$C$35-'02.26'!$C$42),0) -> 0 | E111: =E110+C111-D111 -> 0
B112: 46082 | C112: =IFERROR('03.26'!$C$36+'03.26'!$C$39,0) -> 0 | D112: =IFERROR(MAX(0,'03.26'!$C$35-'03.26'!$C$42),0) -> 0 | E112: =E111+C112-D112 -> 0
B113: 46113 | C113: =IFERROR('04.26'!$C$36+'04.26'!$C$39,0) -> 0 | D113: =IFERROR(MAX(0,'04.26'!$C$35-'04.26'!$C$42),0) -> 0 | E113: =E112+C113-D113 -> 0
B114: 46143 | C114: =IFERROR('05.26'!$C$36+'05.26'!$C$39,0) -> 0 | D114: =IFERROR(MAX(0,'05.26'!$C$35-'05.26'!$C$42),0) -> 0 | E114: =E113+C114-D114 -> 0
B115: 46174 | C115: =IFERROR('06.26'!$C$36+'06.26'!$C$39,0) -> 0 | D115: =IFERROR(MAX(0,'06.26'!$C$35-'06.26'!$C$42),0) -> 0 | E115: =E114+C115-D115 -> 0
B116: 46204 | C116: =IFERROR('07.26'!$C$36+'07.26'!$C$39,0) -> 0 | D116: =IFERROR(MAX(0,'07.26'!$C$35-'07.26'!$C$42),0) -> 0 | E116: =E115+C116-D116 -> 0
B117: 46235 | C117: =IFERROR('08.26'!$C$36+'08.26'!$C$39,0) -> 0 | D117: =IFERROR(MAX(0,'08.26'!$C$35-'08.26'!$C$42),0) -> 0 | E117: =E116+C117-D117 -> 0
B118: 46266 | C118: =IFERROR('09.26'!$C$36+'09.26'!$C$39,0) -> 0 | D118: =IFERROR(MAX(0,'09.26'!$C$35-'09.26'!$C$42),0) -> 0 | E118: =E117+C118-D118 -> 0
B119: 46296 | C119: =IFERROR('10.26'!$C$36+'10.26'!$C$39,0) -> 0 | D119: =IFERROR(MAX(0,'10.26'!$C$35-'10.26'!$C$42),0) -> 0 | E119: =E118+C119-D119 -> 0
B120: 46327 | C120: =IFERROR('11.26'!$C$36+'11.26'!$C$39,0) -> 0 | D120: =IFERROR(MAX(0,'11.26'!$C$35-'11.26'!$C$42),0) -> 0 | E120: =E119+C120-D120 -> 0
B121: 46357 | C121: =IFERROR('12.26'!$C$36+'12.26'!$C$39,0) -> 0 | D121: =IFERROR(MAX(0,'12.26'!$C$35-'12.26'!$C$42),0) -> 0 | E121: =E120+C121-D121 -> 0
B124: COMPENSAÇÃO DE IR. RETIDO NA FONTE EM FIIS.
B125: MÊS | C125: IR. RETIDO NO MÊS | D125: IR. COMPENSADO | E125: ACUMULADO
B126: 46023 | C126: =IFERROR('01.26'!$B$56,0) -> 0 | D126: =IFERROR(MAX(0,'01.26'!$B$54-'01.26'!$B$59),0) -> 0 | E126: =C126-D126 -> 0
B127: 46054 | C127: =IFERROR('02.26'!$B$56,0) -> 0 | D127: =IFERROR(MAX(0,'02.26'!$B$54-'02.26'!$B$59),0) -> 0 | E127: =E126+C127-D127 -> 0
B128: 46082 | C128: =IFERROR('03.26'!$B$56,0) -> 0 | D128: =IFERROR(MAX(0,'03.26'!$B$54-'03.26'!$B$59),0) -> 0 | E128: =E127+C128-D128 -> 0
B129: 46113 | C129: =IFERROR('04.26'!$B$56,0) -> 0 | D129: =IFERROR(MAX(0,'04.26'!$B$54-'04.26'!$B$59),0) -> 0 | E129: =E128+C129-D129 -> 0
B130: 46143 | C130: =IFERROR('05.26'!$B$56,0) -> 0 | D130: =IFERROR(MAX(0,'05.26'!$B$54-'05.26'!$B$59),0) -> 0 | E130: =E129+C130-D130 -> 0
B131: 46174 | C131: =IFERROR('06.26'!$B$56,0) -> 0 | D131: =IFERROR(MAX(0,'06.26'!$B$54-'06.26'!$B$59),0) -> 0 | E131: =E130+C131-D131 -> 0
B132: 46204 | C132: =IFERROR('07.26'!$B$56,0) -> 0 | D132: =IFERROR(MAX(0,'07.26'!$B$54-'07.26'!$B$59),0) -> 0 | E132: =E131+C132-D132 -> 0
B133: 46235 | C133: =IFERROR('08.26'!$B$56,0) -> 0 | D133: =IFERROR(MAX(0,'08.26'!$B$54-'08.26'!$B$59),0) -> 0 | E133: =E132+C133-D133 -> 0
B134: 46266 | C134: =IFERROR('09.26'!$B$56,0) -> 0 | D134: =IFERROR(MAX(0,'09.26'!$B$54-'09.26'!$B$59),0) -> 0 | E134: =E133+C134-D134 -> 0
B135: 46296 | C135: =IFERROR('10.26'!$B$56,0) -> 0 | D135: =IFERROR(MAX(0,'10.26'!$B$54-'10.26'!$B$59),0) -> 0 | E135: =E134+C135-D135 -> 0
B136: 46327 | C136: =IFERROR('11.26'!$B$56,0) -> 0 | D136: =IFERROR(MAX(0,'11.26'!$B$54-'11.26'!$B$59),0) -> 0 | E136: =E135+C136-D136 -> 0
B137: 46357 | C137: =IFERROR('12.26'!$B$56,0) -> 0 | D137: =IFERROR(MAX(0,'12.26'!$B$54-'12.26'!$B$59),0) -> 0 | E137: =E136+C137-D137 -> 0
A151: =A102 -> PERÍODO DE APURAÇÃO: 2026
A152: =A103 -> INVESTIDOR:
A153: =A104 -> CPF:
A155: RESULTADO ANUAL
B157: ACOMPANHAMENTO DE DARF'S.
B158: MÊS | C158: VALOR | D158: IR. COMPENSADO | E158: TOTAL
B159: 46023 | C159: 0 | D159: 0 | E159: =C159-D159 -> 0
B160: 46054 | C160: 0 | D160: 0 | E160: =C160-D160 -> 0
B161: 46082 | C161: 0 | D161: 0 | E161: =C161-D161 -> 0
B162: 46113 | C162: 0 | D162: 0 | E162: =C162-D162 -> 0
B163: 46143 | C163: 0 | D163: 0 | E163: =C163-D163 -> 0
B164: 46174 | C164: 0 | D164: 0 | E164: =C164-D164 -> 0
B165: 46204 | C165: 0 | D165: 0 | E165: =C165-D165 -> 0
B166: 46235 | C166: 0 | D166: 0 | E166: =C166-D166 -> 0
B167: 46266 | C167: 0 | D167: 0 | E167: =C167-D167 -> 0
...

Sheet 01.26
A6: PERÍODO DE APURAÇÃO: 01.26
A7: INVESTIDOR:
A8: CPF:
A10: OPERAÇÕES RENDA VARIÁVEL
B14: SWING TRADE | C14: DAY TRADE: | F14: Informações complementares:
A15: Mercado à vista - ações:
A16: Mercado à vista - ouro: | F16: Isenção de IR
A18: Mercado de opções: | F18: I. Referente à alienação até R$ 20 mil no mercado à vista
A19: Mercado de opções flexíveis:
A20: Mercado à termo: | G20: Alienações (Vendas) | J20: Ganho Isento
F21: Ação | G21: 0 | J21: 0
A22: Mercado futuro - dólar:
A23: Mercado futuro - índices: | F23: Ouro | G23: 0 | J23: 0
A24: Mercado futuro - juros:
A25: Mercado futuro - outros:
F26: II. Referente à ações de pequenas e médias empresas
A27: RESULTADO LÍQUIDO DO MÊS | B27: =SUM(B15:B25) -> 0 | C27: =SUM(C15:C25) -> 0
A28: Resultado negativo até o mês anterior | B28: ='2026'!E32 -> 0 | C28: ='2026'!E12 -> 0 | G28: Ativos isentos op. ST | J28: Ativos isentos op. DT
A29: BASE DE CÁLCULO DO IMPOSTO: | B29: =MAX(0,B27+B28) -> 0 | C29: =MAX(0,C27+C28) -> 0 | F29: Ação | G29: 0 | J29: 0
A30: Prejuízo à compensar | B30: =MIN(0,B27+B28) -> 0 | C30: =MIN(0,C27+C28) -> 0
A31: ALÍQUOTA DO IMPOSTO (%): | B31: 0.15 | C31: 0.2 | F31: Ouro | G31: 0 | J31: 0
A32: IMPOSTO DEVIDO: | B32: =B29*B31 -> 0 | C32: =C29*C31 -> 0
A34: CONSOLIDAÇÃO DO MÊS
A35: Total do imposto devido: | C35: =B32+C32 -> 0 | F35: IR fonte (lei 11.033)
A36: IR Retido na fonte em day trade no mês:
A37: IR Retido na fonte em day trade nos meses anteriores: | F37: Recolhido apenas se o valor mensal for maior que R$ 1
A38: IR Retido na fonte em day trade à compensar: | C38: =MAX(0,C36+C37-C32) -> 0
A39: IR Retido na fonte em swing trade no mês: | F39: Calculo do mês | I39: 0
A40: IR Retido na fonte em swing trade nos meses anteriores: | F40: Recolhido no mês | I40: 0
A41: IR Retido na fonte em swing trade à compensar: | C41: =MAX(0,C39+C40-B32) -> 0 | F41: Meses anteriores | I41: 0
A42: Imposto à pagar: | C42: =MAX(0,C32-(C36+C37))+MAX(0,B32-(C39+C40)) -> 0 | F42: Compensado | I42: 0
A43: Vencimento em: | C43: =IF($C$42>=10,WORKDAY(EOMONTH(DATE(2000+VALUE(RIGHT($A$6,2)),VALUE(MID($A$6,FIND(": ",$A$6)+2,2)),1),1)+1,-1),"") | F43: À compensar até dezembro | I43: 0
A47: Operações de Fundo de Investimento imobiliário e/ou Fiagros
A49: Resultado líquido do mês: | F49: Detalhamento do IR fonte (lei 11.033)
A50: Valor negativo até o mês anterior: | B50: ='2026'!E61 -> 0
A51: Base de cálculo do imposto: | B51: =MAX(0,B49+B50) -> 0 | F51: Recolhido apenas se o valor mensal for maior que R$ 1
A52: Prejuízo à compensar: | B52: =MIN(0,B49+B50) -> 0
A53: ALÍQUOTA DO IMPOSTO (%): | B53: 0.2 | F53: Calculo do mês | I53: 0
A54: IMPOSTO DEVIDO | B54: =B51*B53 -> 0 | F54: Recolhido no mês | I54: 0
F55: Meses anteriores | I55: 0
A56: IR Retido na fonte no mês: | F56: Compensado | I56: 0
A57: IR Retido na fonte nos meses anteriores: | F57: À compensar até dezembro | I57: 0
A58: IR Retido na fonte à compensar: | B58: =MAX(0,B56+B57-B54) -> 0
A59: Imposto à pagar: | B59: =MAX(0,B54-(B56+B57)) -> 0
A60: Vencimento em: | B60: =IF($B$59>=10,WORKDAY(EOMONTH(DATE(2000+VALUE(RIGHT($A$6,2)),VALUE(MID($A$6,FIND(": ",$A$6)+2,2)),1),1)+1,-1),"")

Sheet 02.26
A6: PERÍODO DE APURAÇÃO: 02.26
A7: INVESTIDOR:
A8: CPF:
A10: OPERAÇÕES RENDA VARIÁVEL
B14: SWING TRADE | C14: DAY TRADE: | F14: Informações complementares:
A15: Mercado à vista - ações:
A16: Mercado à vista - ouro: | F16: Isenção de IR
A18: Mercado de opções: | F18: I. Referente à alienação até R$ 20 mil no mercado à vista
A19: Mercado de opções flexíveis:
A20: Mercado à termo: | G20: Alienações (Vendas) | J20: Ganho Isento
F21: Ação | G21: 0 | J21: 0
A22: Mercado futuro - dólar:
A23: Mercado futuro - índices: | F23: Ouro | G23: 0 | J23: 0
A24: Mercado futuro - juros:
A25: Mercado futuro - outros:
F26: II. Referente à ações de pequenas e médias empresas
A27: RESULTADO LÍQUIDO DO MÊS | B27: =SUM(B15:B25) -> 0 | C27: =SUM(C15:C25) -> 0
A28: Resultado negativo até o mês anterior | B28: ='01.26'!B30 -> 0 | C28: ='01.26'!C30 -> 0 | G28: Ativos isentos op. ST | J28: Ativos isentos op. DT
A29: BASE DE CÁLCULO DO IMPOSTO: | B29: =MAX(0,B27+B28) -> 0 | C29: =MAX(0,C27+C28) -> 0 | F29: Ação | G29: 0 | J29: 0
A30: Prejuízo à compensar | B30: =MIN(0,B27+B28) -> 0 | C30: =MIN(0,C27+C28) -> 0
A31: ALÍQUOTA DO IMPOSTO (%): | B31: 0.15 | C31: 0.2 | F31: Ouro | G31: 0 | J31: 0
A32: IMPOSTO DEVIDO: | B32: =B29*B31 -> 0 | C32: =C29*C31 -> 0
A34: CONSOLIDAÇÃO DO MÊS
A35: Total do imposto devido: | C35: =B32+C32 -> 0 | F35: IR fonte (lei 11.033)
A36: IR Retido na fonte em day trade no mês:
A37: IR Retido na fonte em day trade nos meses anteriores: | C37: ='01.26'!C38 -> 0 | F37: Recolhido apenas se o valor mensal for maior que R$ 1
A38: IR Retido na fonte em day trade à compensar: | C38: =MAX(0,C36+C37-C32) -> 0
A39: IR Retido na fonte em swing trade no mês: | F39: Calculo do mês | I39: 0
A40: IR Retido na fonte em swing trade nos meses anteriores: | C40: ='01.26'!C41 -> 0 | F40: Recolhido no mês | I40: 0
A41: IR Retido na fonte em swing trade à compensar: | C41: =MAX(0,C39+C40-B32) -> 0 | F41: Meses anteriores | I41: 0
A42: Imposto à pagar: | C42: =MAX(0,C32-(C36+C37))+MAX(0,B32-(C39+C40)) -> 0 | F42: Compensado | I42: 0
A43: Vencimento em: | C43: =IF($C$42>=10,WORKDAY(EOMONTH(DATE(2000+VALUE(RIGHT($A$6,2)),VALUE(MID($A$6,FIND(": ",$A$6)+2,2)),1),1)+1,-1),"") | F43: À compensar até dezembro | I43: 0
A47: Operações de Fundo de Investimento imobiliário e/ou Fiagros
A49: Resultado líquido do mês: | F49: Detalhamento do IR fonte (lei 11.033)
A50: Valor negativo até o mês anterior: | B50: ='01.26'!B52 -> 0
A51: Base de cálculo do imposto: | B51: =MAX(0,B49+B50) -> 0 | F51: Recolhido apenas se o valor mensal for maior que R$ 1
A52: Prejuízo à compensar: | B52: =MIN(0,B49+B50) -> 0
A53: ALÍQUOTA DO IMPOSTO (%): | B53: 0.2 | F53: Calculo do mês | I53: 0
A54: IMPOSTO DEVIDO | B54: =B51*B53 -> 0 | F54: Recolhido no mês | I54: 0
F55: Meses anteriores | I55: 0
A56: IR Retido na fonte no mês: | F56: Compensado | I56: 0
A57: IR Retido na fonte nos meses anteriores: | B57: ='01.26'!B58 -> 0 | F57: À compensar até dezembro | I57: 0
A58: IR Retido na fonte à compensar: | B58: =MAX(0,B56+B57-B54) -> 0
A59: Imposto à pagar: | B59: =MAX(0,B54-(B56+B57)) -> 0
A60: Vencimento em: | B60: =IF($B$59>=10,WORKDAY(EOMONTH(DATE(2000+VALUE(RIGHT($A$6,2)),VALUE(MID($A$6,FIND(": ",$A$6)+2,2)),1),1)+1,-1),"")

Sheet 03.26
A6: PERÍODO DE APURAÇÃO: 03.26
A7: INVESTIDOR:
A8: CPF:
A10: OPERAÇÕES RENDA VARIÁVEL
B14: SWING TRADE | C14: DAY TRADE: | F14: Informações complementares:
A15: Mercado à vista - ações:
A16: Mercado à vista - ouro: | F16: Isenção de IR
A18: Mercado de opções: | F18: I. Referente à alienação até R$ 20 mil no mercado à vista
A19: Mercado de opções flexíveis:
A20: Mercado à termo: | G20: Alienações (Vendas) | J20: Ganho Isento
F21: Ação | G21: 0 | J21: 0
A22: Mercado futuro - dólar:
A23: Mercado futuro - índices: | F23: Ouro | G23: 0 | J23: 0
A24: Mercado futuro - juros:
A25: Mercado futuro - outros:
F26: II. Referente à ações de pequenas e médias empresas
A27: RESULTADO LÍQUIDO DO MÊS | B27: =SUM(B15:B25) -> 0 | C27: =SUM(C15:C25) -> 0
A28: Resultado negativo até o mês anterior | B28: ='02.26'!B30 -> 0 | C28: ='02.26'!C30 -> 0 | G28: Ativos isentos op. ST | J28: Ativos isentos op. DT
A29: BASE DE CÁLCULO DO IMPOSTO: | B29: =MAX(0,B27+B28) -> 0 | C29: =MAX(0,C27+C28) -> 0 | F29: Ação | G29: 0 | J29: 0
A30: Prejuízo à compensar | B30: =MIN(0,B27+B28) -> 0 | C30: =MIN(0,C27+C28) -> 0
A31: ALÍQUOTA DO IMPOSTO (%): | B31: 0.15 | C31: 0.2 | F31: Ouro | G31: 0 | J31: 0
A32: IMPOSTO DEVIDO: | B32: =B29*B31 -> 0 | C32: =C29*C31 -> 0
A34: CONSOLIDAÇÃO DO MÊS
A35: Total do imposto devido: | C35: =B32+C32 -> 0 | F35: IR fonte (lei 11.033)
A36: IR Retido na fonte em day trade no mês:
A37: IR Retido na fonte em day trade nos meses anteriores: | C37: ='02.26'!C38 -> 0 | F37: Recolhido apenas se o valor mensal for maior que R$ 1
A38: IR Retido na fonte em day trade à compensar: | C38: =MAX(0,C36+C37-C32) -> 0
A39: IR Retido na fonte em swing trade no mês: | F39: Calculo do mês | I39: 0
A40: IR Retido na fonte em swing trade nos meses anteriores: | C40: ='02.26'!C41 -> 0 | F40: Recolhido no mês | I40: 0
A41: IR Retido na fonte em swing trade à compensar: | C41: =MAX(0,C39+C40-B32) -> 0 | F41: Meses anteriores | I41: 0
A42: Imposto à pagar: | C42: =MAX(0,C32-(C36+C37))+MAX(0,B32-(C39+C40)) -> 0 | F42: Compensado | I42: 0
A43: Vencimento em: | C43: =IF($C$42>=10,WORKDAY(EOMONTH(DATE(2000+VALUE(RIGHT($A$6,2)),VALUE(MID($A$6,FIND(": ",$A$6)+2,2)),1),1)+1,-1),"") | F43: À compensar até dezembro | I43: 0
A47: Operações de Fundo de Investimento imobiliário e/ou Fiagros
A49: Resultado líquido do mês: | F49: Detalhamento do IR fonte (lei 11.033)
A50: Valor negativo até o mês anterior: | B50: ='02.26'!B52 -> 0
A51: Base de cálculo do imposto: | B51: =MAX(0,B49+B50) -> 0 | F51: Recolhido apenas se o valor mensal for maior que R$ 1
A52: Prejuízo à compensar: | B52: =MIN(0,B49+B50) -> 0
A53: ALÍQUOTA DO IMPOSTO (%): | B53: 0.2 | F53: Calculo do mês | I53: 0
A54: IMPOSTO DEVIDO | B54: =B51*B53 -> 0 | F54: Recolhido no mês | I54: 0
F55: Meses anteriores | I55: 0
A56: IR Retido na fonte no mês: | F56: Compensado | I56: 0
A57: IR Retido na fonte nos meses anteriores: | B57: ='02.26'!B58 -> 0 | F57: À compensar até dezembro | I57: 0
A58: IR Retido na fonte à compensar: | B58: =MAX(0,B56+B57-B54) -> 0
A59: Imposto à pagar: | B59: =MAX(0,B54-(B56+B57)) -> 0
A60: Vencimento em: | B60: =IF($B$59>=10,WORKDAY(EOMONTH(DATE(2000+VALUE(RIGHT($A$6,2)),VALUE(MID($A$6,FIND(": ",$A$6)+2,2)),1),1)+1,-1),"")

Sheet 04.26
A6: PERÍODO DE APURAÇÃO: 04.26
A7: INVESTIDOR:
A8: CPF:
A10: OPERAÇÕES RENDA VARIÁVEL
B14: SWING TRADE | C14: DAY TRADE: | F14: Informações complementares:
A15: Mercado à vista - ações:
A16: Mercado à vista - ouro: | F16: Isenção de IR
A18: Mercado de opções: | F18: I. Referente à alienação até R$ 20 mil no mercado à vista
A19: Mercado de opções flexíveis:
A20: Mercado à termo: | G20: Alienações (Vendas) | J20: Ganho Isento
F21: Ação | G21: 0 | J21: 0
A22: Mercado futuro - dólar:
A23: Mercado futuro - índices: | F23: Ouro | G23: 0 | J23: 0
A24: Mercado futuro - juros:
A25: Mercado futuro - outros:
F26: II. Referente à ações de pequenas e médias empresas
A27: RESULTADO LÍQUIDO DO MÊS | B27: =SUM(B15:B25) -> 0 | C27: =SUM(C15:C25) -> 0
A28: Resultado negativo até o mês anterior | B28: ='03.26'!B30 -> 0 | C28: ='03.26'!C30 -> 0 | G28: Ativos isentos op. ST | J28: Ativos isentos op. DT
A29: BASE DE CÁLCULO DO IMPOSTO: | B29: =MAX(0,B27+B28) -> 0 | C29: =MAX(0,C27+C28) -> 0 | F29: Ação | G29: 0 | J29: 0
A30: Prejuízo à compensar | B30: =MIN(0,B27+B28) -> 0 | C30: =MIN(0,C27+C28) -> 0
A31: ALÍQUOTA DO IMPOSTO (%): | B31: 0.15 | C31: 0.2 | F31: Ouro | G31: 0 | J31: 0
A32: IMPOSTO DEVIDO: | B32: =B29*B31 -> 0 | C32: =C29*C31 -> 0
A34: CONSOLIDAÇÃO DO MÊS
A35: Total do imposto devido: | C35: =B32+C32 -> 0 | F35: IR fonte (lei 11.033)
A36: IR Retido na fonte em day trade no mês:
A37: IR Retido na fonte em day trade nos meses anteriores: | C37: ='03.26'!C38 -> 0 | F37: Recolhido apenas se o valor mensal for maior que R$ 1
A38: IR Retido na fonte em day trade à compensar: | C38: =MAX(0,C36+C37-C32) -> 0
A39: IR Retido na fonte em swing trade no mês: | F39: Calculo do mês | I39: 0
A40: IR Retido na fonte em swing trade nos meses anteriores: | C40: ='03.26'!C41 -> 0 | F40: Recolhido no mês | I40: 0
A41: IR Retido na fonte em swing trade à compensar: | C41: =MAX(0,C39+C40-B32) -> 0 | F41: Meses anteriores | I41: 0
A42: Imposto à pagar: | C42: =MAX(0,C32-(C36+C37))+MAX(0,B32-(C39+C40)) -> 0 | F42: Compensado | I42: 0
A43: Vencimento em: | C43: =IF($C$42>=10,WORKDAY(EOMONTH(DATE(2000+VALUE(RIGHT($A$6,2)),VALUE(MID($A$6,FIND(": ",$A$6)+2,2)),1),1)+1,-1),"") | F43: À compensar até dezembro | I43: 0
A47: Operações de Fundo de Investimento imobiliário e/ou Fiagros
A49: Resultado líquido do mês: | F49: Detalhamento do IR fonte (lei 11.033)
A50: Valor negativo até o mês anterior: | B50: ='03.26'!B52 -> 0
A51: Base de cálculo do imposto: | B51: =MAX(0,B49+B50) -> 0 | F51: Recolhido apenas se o valor mensal for maior que R$ 1
A52: Prejuízo à compensar: | B52: =MIN(0,B49+B50) -> 0
A53: ALÍQUOTA DO IMPOSTO (%): | B53: 0.2 | F53: Calculo do mês | I53: 0
A54: IMPOSTO DEVIDO | B54: =B51*B53 -> 0 | F54: Recolhido no mês | I54: 0
F55: Meses anteriores | I55: 0
A56: IR Retido na fonte no mês: | F56: Compensado | I56: 0
A57: IR Retido na fonte nos meses anteriores: | B57: ='03.26'!B58 -> 0 | F57: À compensar até dezembro | I57: 0
A58: IR Retido na fonte à compensar: | B58: =MAX(0,B56+B57-B54) -> 0
A59: Imposto à pagar: | B59: =MAX(0,B54-(B56+B57)) -> 0
A60: Vencimento em: | B60: =IF($B$59>=10,WORKDAY(EOMONTH(DATE(2000+VALUE(RIGHT($A$6,2)),VALUE(MID($A$6,FIND(": ",$A$6)+2,2)),1),1)+1,-1),"")

Sheet 05.26
A6: PERÍODO DE APURAÇÃO: 05.26
A7: INVESTIDOR:
A8: CPF:
A10: OPERAÇÕES RENDA VARIÁVEL
B14: SWING TRADE | C14: DAY TRADE: | F14: Informações complementares:
A15: Mercado à vista - ações:
A16: Mercado à vista - ouro: | F16: Isenção de IR
A18: Mercado de opções: | F18: I. Referente à alienação até R$ 20 mil no mercado à vista
A19: Mercado de opções flexíveis:
A20: Mercado à termo: | G20: Alienações (Vendas) | J20: Ganho Isento
F21: Ação | G21: 0 | J21: 0
A22: Mercado futuro - dólar:
A23: Mercado futuro - índices: | F23: Ouro | G23: 0 | J23: 0
A24: Mercado futuro - juros:
A25: Mercado futuro - outros:
F26: II. Referente à ações de pequenas e médias empresas
A27: RESULTADO LÍQUIDO DO MÊS | B27: =SUM(B15:B25) -> 0 | C27: =SUM(C15:C25) -> 0
A28: Resultado negativo até o mês anterior | B28: ='04.26'!B30 -> 0 | C28: ='04.26'!C30 -> 0 | G28: Ativos isentos op. ST | J28: Ativos isentos op. DT
A29: BASE DE CÁLCULO DO IMPOSTO: | B29: =MAX(0,B27+B28) -> 0 | C29: =MAX(0,C27+C28) -> 0 | F29: Ação | G29: 0 | J29: 0
A30: Prejuízo à compensar | B30: =MIN(0,B27+B28) -> 0 | C30: =MIN(0,C27+C28) -> 0
A31: ALÍQUOTA DO IMPOSTO (%): | B31: 0.15 | C31: 0.2 | F31: Ouro | G31: 0 | J31: 0
A32: IMPOSTO DEVIDO: | B32: =B29*B31 -> 0 | C32: =C29*C31 -> 0
A34: CONSOLIDAÇÃO DO MÊS
A35: Total do imposto devido: | C35: =B32+C32 -> 0 | F35: IR fonte (lei 11.033)
A36: IR Retido na fonte em day trade no mês:
A37: IR Retido na fonte em day trade nos meses anteriores: | C37: ='04.26'!C38 -> 0 | F37: Recolhido apenas se o valor mensal for maior que R$ 1
A38: IR Retido na fonte em day trade à compensar: | C38: =MAX(0,C36+C37-C32) -> 0
A39: IR Retido na fonte em swing trade no mês: | F39: Calculo do mês | I39: 0
A40: IR Retido na fonte em swing trade nos meses anteriores: | C40: ='04.26'!C41 -> 0 | F40: Recolhido no mês | I40: 0
A41: IR Retido na fonte em swing trade à compensar: | C41: =MAX(0,C39+C40-B32) -> 0 | F41: Meses anteriores | I41: 0
A42: Imposto à pagar: | C42: =MAX(0,C32-(C36+C37))+MAX(0,B32-(C39+C40)) -> 0 | F42: Compensado | I42: 0
A43: Vencimento em: | C43: =IF($C$42>=10,WORKDAY(EOMONTH(DATE(2000+VALUE(RIGHT($A$6,2)),VALUE(MID($A$6,FIND(": ",$A$6)+2,2)),1),1)+1,-1),"") | F43: À compensar até dezembro | I43: 0
A47: Operações de Fundo de Investimento imobiliário e/ou Fiagros
A49: Resultado líquido do mês: | F49: Detalhamento do IR fonte (lei 11.033)
A50: Valor negativo até o mês anterior: | B50: ='04.26'!B52 -> 0
A51: Base de cálculo do imposto: | B51: =MAX(0,B49+B50) -> 0 | F51: Recolhido apenas se o valor mensal for maior que R$ 1
A52: Prejuízo à compensar: | B52: =MIN(0,B49+B50) -> 0
A53: ALÍQUOTA DO IMPOSTO (%): | B53: 0.2 | F53: Calculo do mês | I53: 0
A54: IMPOSTO DEVIDO | B54: =B51*B53 -> 0 | F54: Recolhido no mês | I54: 0
F55: Meses anteriores | I55: 0
A56: IR Retido na fonte no mês: | F56: Compensado | I56: 0
A57: IR Retido na fonte nos meses anteriores: | B57: ='04.26'!B58 -> 0 | F57: À compensar até dezembro | I57: 0
A58: IR Retido na fonte à compensar: | B58: =MAX(0,B56+B57-B54) -> 0
A59: Imposto à pagar: | B59: =MAX(0,B54-(B56+B57)) -> 0
A60: Vencimento em: | B60: =IF($B$59>=10,WORKDAY(EOMONTH(DATE(2000+VALUE(RIGHT($A$6,2)),VALUE(MID($A$6,FIND(": ",$A$6)+2,2)),1),1)+1,-1),"")

Sheet 06.26
A6: PERÍODO DE APURAÇÃO: 06.26
A7: INVESTIDOR:
A8: CPF:
A10: OPERAÇÕES RENDA VARIÁVEL
B14: SWING TRADE | C14: DAY TRADE: | F14: Informações complementares:
A15: Mercado à vista - ações:
A16: Mercado à vista - ouro: | F16: Isenção de IR
A18: Mercado de opções: | F18: I. Referente à alienação até R$ 20 mil no mercado à vista
A19: Mercado de opções flexíveis:
A20: Mercado à termo: | G20: Alienações (Vendas) | J20: Ganho Isento
F21: Ação | G21: 0 | J21: 0
A22: Mercado futuro - dólar:
A23: Mercado futuro - índices: | F23: Ouro | G23: 0 | J23: 0
A24: Mercado futuro - juros:
A25: Mercado futuro - outros:
F26: II. Referente à ações de pequenas e médias empresas
A27: RESULTADO LÍQUIDO DO MÊS | B27: =SUM(B15:B25) -> 0 | C27: =SUM(C15:C25) -> 0
A28: Resultado negativo até o mês anterior | B28: ='05.26'!B30 -> 0 | C28: ='05.26'!C30 -> 0 | G28: Ativos isentos op. ST | J28: Ativos isentos op. DT
A29: BASE DE CÁLCULO DO IMPOSTO: | B29: =MAX(0,B27+B28) -> 0 | C29: =MAX(0,C27+C28) -> 0 | F29: Ação | G29: 0 | J29: 0
A30: Prejuízo à compensar | B30: =MIN(0,B27+B28) -> 0 | C30: =MIN(0,C27+C28) -> 0
A31: ALÍQUOTA DO IMPOSTO (%): | B31: 0.15 | C31: 0.2 | F31: Ouro | G31: 0 | J31: 0
A32: IMPOSTO DEVIDO: | B32: =B29*B31 -> 0 | C32: =C29*C31 -> 0
A34: CONSOLIDAÇÃO DO MÊS
A35: Total do imposto devido: | C35: =B32+C32 -> 0 | F35: IR fonte (lei 11.033)
A36: IR Retido na fonte em day trade no mês:
A37: IR Retido na fonte em day trade nos meses anteriores: | C37: ='05.26'!C38 -> 0 | F37: Recolhido apenas se o valor mensal for maior que R$ 1
A38: IR Retido na fonte em day trade à compensar: | C38: =MAX(0,C36+C37-C32) -> 0
A39: IR Retido na fonte em swing trade no mês: | F39: Calculo do mês | I39: 0
A40: IR Retido na fonte em swing trade nos meses anteriores: | C40: ='05.26'!C41 -> 0 | F40: Recolhido no mês | I40: 0
A41: IR Retido na fonte em swing trade à compensar: | C41: =MAX(0,C39+C40-B32) -> 0 | F41: Meses anteriores | I41: 0
A42: Imposto à pagar: | C42: =MAX(0,C32-(C36+C37))+MAX(0,B32-(C39+C40)) -> 0 | F42: Compensado | I42: 0
A43: Vencimento em: | C43: =IF($C$42>=10,WORKDAY(EOMONTH(DATE(2000+VALUE(RIGHT($A$6,2)),VALUE(MID($A$6,FIND(": ",$A$6)+2,2)),1),1)+1,-1),"") | F43: À compensar até dezembro | I43: 0
A47: Operações de Fundo de Investimento imobiliário e/ou Fiagros
A49: Resultado líquido do mês: | F49: Detalhamento do IR fonte (lei 11.033)
A50: Valor negativo até o mês anterior: | B50: ='05.26'!B52 -> 0
A51: Base de cálculo do imposto: | B51: =MAX(0,B49+B50) -> 0 | F51: Recolhido apenas se o valor mensal for maior que R$ 1
A52: Prejuízo à compensar: | B52: =MIN(0,B49+B50) -> 0
A53: ALÍQUOTA DO IMPOSTO (%): | B53: 0.2 | F53: Calculo do mês | I53: 0
A54: IMPOSTO DEVIDO | B54: =B51*B53 -> 0 | F54: Recolhido no mês | I54: 0
F55: Meses anteriores | I55: 0
A56: IR Retido na fonte no mês: | F56: Compensado | I56: 0
A57: IR Retido na fonte nos meses anteriores: | B57: ='05.26'!B58 -> 0 | F57: À compensar até dezembro | I57: 0
A58: IR Retido na fonte à compensar: | B58: =MAX(0,B56+B57-B54) -> 0
A59: Imposto à pagar: | B59: =MAX(0,B54-(B56+B57)) -> 0
A60: Vencimento em: | B60: =IF($B$59>=10,WORKDAY(EOMONTH(DATE(2000+VALUE(RIGHT($A$6,2)),VALUE(MID($A$6,FIND(": ",$A$6)+2,2)),1),1)+1,-1),"")

Sheet 07.26
A6: PERÍODO DE APURAÇÃO: 07.26
A7: INVESTIDOR:
A8: CPF:
A10: OPERAÇÕES RENDA VARIÁVEL
B14: SWING TRADE | C14: DAY TRADE: | F14: Informações complementares:
A15: Mercado à vista - ações:
A16: Mercado à vista - ouro: | F16: Isenção de IR
A18: Mercado de opções: | F18: I. Referente à alienação até R$ 20 mil no mercado à vista
A19: Mercado de opções flexíveis:
A20: Mercado à termo: | G20: Alienações (Vendas) | J20: Ganho Isento
F21: Ação | G21: 0 | J21: 0
A22: Mercado futuro - dólar:
A23: Mercado futuro - índices: | F23: Ouro | G23: 0 | J23: 0
A24: Mercado futuro - juros:
A25: Mercado futuro - outros:
F26: II. Referente à ações de pequenas e médias empresas
A27: RESULTADO LÍQUIDO DO MÊS | B27: =SUM(B15:B25) -> 0 | C27: =SUM(C15:C25) -> 0
A28: Resultado negativo até o mês anterior | B28: ='06.26'!B30 -> 0 | C28: ='06.26'!C30 -> 0 | G28: Ativos isentos op. ST | J28: Ativos isentos op. DT
A29: BASE DE CÁLCULO DO IMPOSTO: | B29: =MAX(0,B27+B28) -> 0 | C29: =MAX(0,C27+C28) -> 0 | F29: Ação | G29: 0 | J29: 0
A30: Prejuízo à compensar | B30: =MIN(0,B27+B28) -> 0 | C30: =MIN(0,C27+C28) -> 0
A31: ALÍQUOTA DO IMPOSTO (%): | B31: 0.15 | C31: 0.2 | F31: Ouro | G31: 0 | J31: 0
A32: IMPOSTO DEVIDO: | B32: =B29*B31 -> 0 | C32: =C29*C31 -> 0
A34: CONSOLIDAÇÃO DO MÊS
A35: Total do imposto devido: | C35: =B32+C32 -> 0 | F35: IR fonte (lei 11.033)
A36: IR Retido na fonte em day trade no mês:
A37: IR Retido na fonte em day trade nos meses anteriores: | C37: ='06.26'!C38 -> 0 | F37: Recolhido apenas se o valor mensal for maior que R$ 1
A38: IR Retido na fonte em day trade à compensar: | C38: =MAX(0,C36+C37-C32) -> 0
A39: IR Retido na fonte em swing trade no mês: | F39: Calculo do mês | I39: 0
A40: IR Retido na fonte em swing trade nos meses anteriores: | C40: ='06.26'!C41 -> 0 | F40: Recolhido no mês | I40: 0
A41: IR Retido na fonte em swing trade à compensar: | C41: =MAX(0,C39+C40-B32) -> 0 | F41: Meses anteriores | I41: 0
A42: Imposto à pagar: | C42: =MAX(0,C32-(C36+C37))+MAX(0,B32-(C39+C40)) -> 0 | F42: Compensado | I42: 0
A43: Vencimento em: | C43: =IF($C$42>=10,WORKDAY(EOMONTH(DATE(2000+VALUE(RIGHT($A$6,2)),VALUE(MID($A$6,FIND(": ",$A$6)+2,2)),1),1)+1,-1),"") | F43: À compensar até dezembro | I43: 0
A47: Operações de Fundo de Investimento imobiliário e/ou Fiagros
A49: Resultado líquido do mês: | F49: Detalhamento do IR fonte (lei 11.033)
A50: Valor negativo até o mês anterior: | B50: ='06.26'!B52 -> 0
A51: Base de cálculo do imposto: | B51: =MAX(0,B49+B50) -> 0 | F51: Recolhido apenas se o valor mensal for maior que R$ 1
A52: Prejuízo à compensar: | B52: =MIN(0,B49+B50) -> 0
A53: ALÍQUOTA DO IMPOSTO (%): | B53: 0.2 | F53: Calculo do mês | I53: 0
A54: IMPOSTO DEVIDO | B54: =B51*B53 -> 0 | F54: Recolhido no mês | I54: 0
F55: Meses anteriores | I55: 0
A56: IR Retido na fonte no mês: | F56: Compensado | I56: 0
A57: IR Retido na fonte nos meses anteriores: | B57: ='06.26'!B58 -> 0 | F57: À compensar até dezembro | I57: 0
A58: IR Retido na fonte à compensar: | B58: =MAX(0,B56+B57-B54) -> 0
A59: Imposto à pagar: | B59: =MAX(0,B54-(B56+B57)) -> 0
A60: Vencimento em: | B60: =IF($B$59>=10,WORKDAY(EOMONTH(DATE(2000+VALUE(RIGHT($A$6,2)),VALUE(MID($A$6,FIND(": ",$A$6)+2,2)),1),1)+1,-1),"")

Sheet 08.26
A6: PERÍODO DE APURAÇÃO: 08.26
A7: INVESTIDOR:
A8: CPF:
A10: OPERAÇÕES RENDA VARIÁVEL
B14: SWING TRADE | C14: DAY TRADE: | F14: Informações complementares:
A15: Mercado à vista - ações:
A16: Mercado à vista - ouro: | F16: Isenção de IR
A18: Mercado de opções: | F18: I. Referente à alienação até R$ 20 mil no mercado à vista
A19: Mercado de opções flexíveis:
A20: Mercado à termo: | G20: Alienações (Vendas) | J20: Ganho Isento
F21: Ação | G21: 0 | J21: 0
A22: Mercado futuro - dólar:
A23: Mercado futuro - índices: | F23: Ouro | G23: 0 | J23: 0
A24: Mercado futuro - juros:
A25: Mercado futuro - outros:
F26: II. Referente à ações de pequenas e médias empresas
A27: RESULTADO LÍQUIDO DO MÊS | B27: =SUM(B15:B25) -> 0 | C27: =SUM(C15:C25) -> 0
A28: Resultado negativo até o mês anterior | B28: ='07.26'!B30 -> 0 | C28: ='07.26'!C30 -> 0 | G28: Ativos isentos op. ST | J28: Ativos isentos op. DT
A29: BASE DE CÁLCULO DO IMPOSTO: | B29: =MAX(0,B27+B28) -> 0 | C29: =MAX(0,C27+C28) -> 0 | F29: Ação | G29: 0 | J29: 0
A30: Prejuízo à compensar | B30: =MIN(0,B27+B28) -> 0 | C30: =MIN(0,C27+C28) -> 0
A31: ALÍQUOTA DO IMPOSTO (%): | B31: 0.15 | C31: 0.2 | F31: Ouro | G31: 0 | J31: 0
A32: IMPOSTO DEVIDO: | B32: =B29*B31 -> 0 | C32: =C29*C31 -> 0
A34: CONSOLIDAÇÃO DO MÊS
A35: Total do imposto devido: | C35: =B32+C32 -> 0 | F35: IR fonte (lei 11.033)
A36: IR Retido na fonte em day trade no mês:
A37: IR Retido na fonte em day trade nos meses anteriores: | C37: ='07.26'!C38 -> 0 | F37: Recolhido apenas se o valor mensal for maior que R$ 1
A38: IR Retido na fonte em day trade à compensar: | C38: =MAX(0,C36+C37-C32) -> 0
A39: IR Retido na fonte em swing trade no mês: | F39: Calculo do mês | I39: 0
A40: IR Retido na fonte em swing trade nos meses anteriores: | C40: ='07.26'!C41 -> 0 | F40: Recolhido no mês | I40: 0
A41: IR Retido na fonte em swing trade à compensar: | C41: =MAX(0,C39+C40-B32) -> 0 | F41: Meses anteriores | I41: 0
A42: Imposto à pagar: | C42: =MAX(0,C32-(C36+C37))+MAX(0,B32-(C39+C40)) -> 0 | F42: Compensado | I42: 0
A43: Vencimento em: | C43: =IF($C$42>=10,WORKDAY(EOMONTH(DATE(2000+VALUE(RIGHT($A$6,2)),VALUE(MID($A$6,FIND(": ",$A$6)+2,2)),1),1)+1,-1),"") | F43: À compensar até dezembro | I43: 0
A47: Operações de Fundo de Investimento imobiliário e/ou Fiagros
A49: Resultado líquido do mês: | F49: Detalhamento do IR fonte (lei 11.033)
A50: Valor negativo até o mês anterior: | B50: ='07.26'!B52 -> 0
A51: Base de cálculo do imposto: | B51: =MAX(0,B49+B50) -> 0 | F51: Recolhido apenas se o valor mensal for maior que R$ 1
A52: Prejuízo à compensar: | B52: =MIN(0,B49+B50) -> 0
A53: ALÍQUOTA DO IMPOSTO (%): | B53: 0.2 | F53: Calculo do mês | I53: 0
A54: IMPOSTO DEVIDO | B54: =B51*B53 -> 0 | F54: Recolhido no mês | I54: 0
F55: Meses anteriores | I55: 0
A56: IR Retido na fonte no mês: | F56: Compensado | I56: 0
A57: IR Retido na fonte nos meses anteriores: | B57: ='07.26'!B58 -> 0 | F57: À compensar até dezembro | I57: 0
A58: IR Retido na fonte à compensar: | B58: =MAX(0,B56+B57-B54) -> 0
A59: Imposto à pagar: | B59: =MAX(0,B54-(B56+B57)) -> 0
A60: Vencimento em: | B60: =IF($B$59>=10,WORKDAY(EOMONTH(DATE(2000+VALUE(RIGHT($A$6,2)),VALUE(MID($A$6,FIND(": ",$A$6)+2,2)),1),1)+1,-1),"")

Sheet 09.26
A6: PERÍODO DE APURAÇÃO: 09.26
A7: INVESTIDOR:
A8: CPF:
A10: OPERAÇÕES RENDA VARIÁVEL
B14: SWING TRADE | C14: DAY TRADE: | F14: Informações complementares:
A15: Mercado à vista - ações:
A16: Mercado à vista - ouro: | F16: Isenção de IR
A18: Mercado de opções: | F18: I. Referente à alienação até R$ 20 mil no mercado à vista
A19: Mercado de opções flexíveis:
A20: Mercado à termo: | G20: Alienações (Vendas) | J20: Ganho Isento
F21: Ação | G21: 0 | J21: 0
A22: Mercado futuro - dólar:
A23: Mercado futuro - índices: | F23: Ouro | G23: 0 | J23: 0
A24: Mercado futuro - juros:
A25: Mercado futuro - outros:
F26: II. Referente à ações de pequenas e médias empresas
A27: RESULTADO LÍQUIDO DO MÊS | B27: =SUM(B15:B25) -> 0 | C27: =SUM(C15:C25) -> 0
A28: Resultado negativo até o mês anterior | B28: ='08.26'!B30 -> 0 | C28: ='08.26'!C30 -> 0 | G28: Ativos isentos op. ST | J28: Ativos isentos op. DT
A29: BASE DE CÁLCULO DO IMPOSTO: | B29: =MAX(0,B27+B28) -> 0 | C29: =MAX(0,C27+C28) -> 0 | F29: Ação | G29: 0 | J29: 0
A30: Prejuízo à compensar | B30: =MIN(0,B27+B28) -> 0 | C30: =MIN(0,C27+C28) -> 0
A31: ALÍQUOTA DO IMPOSTO (%): | B31: 0.15 | C31: 0.2 | F31: Ouro | G31: 0 | J31: 0
A32: IMPOSTO DEVIDO: | B32: =B29*B31 -> 0 | C32: =C29*C31 -> 0
A34: CONSOLIDAÇÃO DO MÊS
A35: Total do imposto devido: | C35: =B32+C32 -> 0 | F35: IR fonte (lei 11.033)
A36: IR Retido na fonte em day trade no mês:
A37: IR Retido na fonte em day trade nos meses anteriores: | C37: ='08.26'!C38 -> 0 | F37: Recolhido apenas se o valor mensal for maior que R$ 1
A38: IR Retido na fonte em day trade à compensar: | C38: =MAX(0,C36+C37-C32) -> 0
A39: IR Retido na fonte em swing trade no mês: | F39: Calculo do mês | I39: 0
A40: IR Retido na fonte em swing trade nos meses anteriores: | C40: ='08.26'!C41 -> 0 | F40: Recolhido no mês | I40: 0
A41: IR Retido na fonte em swing trade à compensar: | C41: =MAX(0,C39+C40-B32) -> 0 | F41: Meses anteriores | I41: 0
A42: Imposto à pagar: | C42: =MAX(0,C32-(C36+C37))+MAX(0,B32-(C39+C40)) -> 0 | F42: Compensado | I42: 0
A43: Vencimento em: | C43: =IF($C$42>=10,WORKDAY(EOMONTH(DATE(2000+VALUE(RIGHT($A$6,2)),VALUE(MID($A$6,FIND(": ",$A$6)+2,2)),1),1)+1,-1),"") | F43: À compensar até dezembro | I43: 0
A47: Operações de Fundo de Investimento imobiliário e/ou Fiagros
A49: Resultado líquido do mês: | F49: Detalhamento do IR fonte (lei 11.033)
A50: Valor negativo até o mês anterior: | B50: ='08.26'!B52 -> 0
A51: Base de cálculo do imposto: | B51: =MAX(0,B49+B50) -> 0 | F51: Recolhido apenas se o valor mensal for maior que R$ 1
A52: Prejuízo à compensar: | B52: =MIN(0,B49+B50) -> 0
A53: ALÍQUOTA DO IMPOSTO (%): | B53: 0.2 | F53: Calculo do mês | I53: 0
A54: IMPOSTO DEVIDO | B54: =B51*B53 -> 0 | F54: Recolhido no mês | I54: 0
F55: Meses anteriores | I55: 0
A56: IR Retido na fonte no mês: | F56: Compensado | I56: 0
A57: IR Retido na fonte nos meses anteriores: | B57: ='08.26'!B58 -> 0 | F57: À compensar até dezembro | I57: 0
A58: IR Retido na fonte à compensar: | B58: =MAX(0,B56+B57-B54) -> 0
A59: Imposto à pagar: | B59: =MAX(0,B54-(B56+B57)) -> 0
A60: Vencimento em: | B60: =IF($B$59>=10,WORKDAY(EOMONTH(DATE(2000+VALUE(RIGHT($A$6,2)),VALUE(MID($A$6,FIND(": ",$A$6)+2,2)),1),1)+1,-1),"")

Sheet 10.26
A6: PERÍODO DE APURAÇÃO: 10.26
A7: INVESTIDOR:
A8: CPF:
A10: OPERAÇÕES RENDA VARIÁVEL
B14: SWING TRADE | C14: DAY TRADE: | F14: Informações complementares:
A15: Mercado à vista - ações:
A16: Mercado à vista - ouro: | F16: Isenção de IR
A18: Mercado de opções: | F18: I. Referente à alienação até R$ 20 mil no mercado à vista
A19: Mercado de opções flexíveis:
A20: Mercado à termo: | G20: Alienações (Vendas) | J20: Ganho Isento
F21: Ação | G21: 0 | J21: 0
A22: Mercado futuro - dólar:
A23: Mercado futuro - índices: | F23: Ouro | G23: 0 | J23: 0
A24: Mercado futuro - juros:
A25: Mercado futuro - outros:
F26: II. Referente à ações de pequenas e médias empresas
A27: RESULTADO LÍQUIDO DO MÊS | B27: =SUM(B15:B25) -> 0 | C27: =SUM(C15:C25) -> 0
A28: Resultado negativo até o mês anterior | B28: ='09.26'!B30 -> 0 | C28: ='09.26'!C30 -> 0 | G28: Ativos isentos op. ST | J28: Ativos isentos op. DT
A29: BASE DE CÁLCULO DO IMPOSTO: | B29: =MAX(0,B27+B28) -> 0 | C29: =MAX(0,C27+C28) -> 0 | F29: Ação | G29: 0 | J29: 0
A30: Prejuízo à compensar | B30: =MIN(0,B27+B28) -> 0 | C30: =MIN(0,C27+C28) -> 0
A31: ALÍQUOTA DO IMPOSTO (%): | B31: 0.15 | C31: 0.2 | F31: Ouro | G31: 0 | J31: 0
A32: IMPOSTO DEVIDO: | B32: =B29*B31 -> 0 | C32: =C29*C31 -> 0
A34: CONSOLIDAÇÃO DO MÊS
A35: Total do imposto devido: | C35: =B32+C32 -> 0 | F35: IR fonte (lei 11.033)
A36: IR Retido na fonte em day trade no mês:
A37: IR Retido na fonte em day trade nos meses anteriores: | C37: ='09.26'!C38 -> 0 | F37: Recolhido apenas se o valor mensal for maior que R$ 1
A38: IR Retido na fonte em day trade à compensar: | C38: =MAX(0,C36+C37-C32) -> 0
A39: IR Retido na fonte em swing trade no mês: | F39: Calculo do mês | I39: 0
A40: IR Retido na fonte em swing trade nos meses anteriores: | C40: ='09.26'!C41 -> 0 | F40: Recolhido no mês | I40: 0
A41: IR Retido na fonte em swing trade à compensar: | C41: =MAX(0,C39+C40-B32) -> 0 | F41: Meses anteriores | I41: 0
A42: Imposto à pagar: | C42: =MAX(0,C32-(C36+C37))+MAX(0,B32-(C39+C40)) -> 0 | F42: Compensado | I42: 0
A43: Vencimento em: | C43: =IF($C$42>=10,WORKDAY(EOMONTH(DATE(2000+VALUE(RIGHT($A$6,2)),VALUE(MID($A$6,FIND(": ",$A$6)+2,2)),1),1)+1,-1),"") | F43: À compensar até dezembro | I43: 0
A47: Operações de Fundo de Investimento imobiliário e/ou Fiagros
A49: Resultado líquido do mês: | F49: Detalhamento do IR fonte (lei 11.033)
A50: Valor negativo até o mês anterior: | B50: ='09.26'!B52 -> 0
A51: Base de cálculo do imposto: | B51: =MAX(0,B49+B50) -> 0 | F51: Recolhido apenas se o valor mensal for maior que R$ 1
A52: Prejuízo à compensar: | B52: =MIN(0,B49+B50) -> 0
A53: ALÍQUOTA DO IMPOSTO (%): | B53: 0.2 | F53: Calculo do mês | I53: 0
A54: IMPOSTO DEVIDO | B54: =B51*B53 -> 0 | F54: Recolhido no mês | I54: 0
F55: Meses anteriores | I55: 0
A56: IR Retido na fonte no mês: | F56: Compensado | I56: 0
A57: IR Retido na fonte nos meses anteriores: | B57: ='09.26'!B58 -> 0 | F57: À compensar até dezembro | I57: 0
A58: IR Retido na fonte à compensar: | B58: =MAX(0,B56+B57-B54) -> 0
A59: Imposto à pagar: | B59: =MAX(0,B54-(B56+B57)) -> 0
A60: Vencimento em: | B60: =IF($B$59>=10,WORKDAY(EOMONTH(DATE(2000+VALUE(RIGHT($A$6,2)),VALUE(MID($A$6,FIND(": ",$A$6)+2,2)),1),1)+1,-1),"")

Sheet 11.26
A6: PERÍODO DE APURAÇÃO: 11.26
A7: INVESTIDOR:
A8: CPF:
A10: OPERAÇÕES RENDA VARIÁVEL
B14: SWING TRADE | C14: DAY TRADE: | F14: Informações complementares:
A15: Mercado à vista - ações:
A16: Mercado à vista - ouro: | F16: Isenção de IR
A18: Mercado de opções: | F18: I. Referente à alienação até R$ 20 mil no mercado à vista
A19: Mercado de opções flexíveis:
A20: Mercado à termo: | G20: Alienações (Vendas) | J20: Ganho Isento
F21: Ação | G21: 0 | J21: 0
A22: Mercado futuro - dólar:
A23: Mercado futuro - índices: | F23: Ouro | G23: 0 | J23: 0
A24: Mercado futuro - juros:
A25: Mercado futuro - outros:
F26: II. Referente à ações de pequenas e médias empresas
A27: RESULTADO LÍQUIDO DO MÊS | B27: =SUM(B15:B25) -> 0 | C27: =SUM(C15:C25) -> 0
A28: Resultado negativo até o mês anterior | B28: ='10.26'!B30 -> 0 | C28: ='10.26'!C30 -> 0 | G28: Ativos isentos op. ST | J28: Ativos isentos op. DT
A29: BASE DE CÁLCULO DO IMPOSTO: | B29: =MAX(0,B27+B28) -> 0 | C29: =MAX(0,C27+C28) -> 0 | F29: Ação | G29: 0 | J29: 0
A30: Prejuízo à compensar | B30: =MIN(0,B27+B28) -> 0 | C30: =MIN(0,C27+C28) -> 0
A31: ALÍQUOTA DO IMPOSTO (%): | B31: 0.15 | C31: 0.2 | F31: Ouro | G31: 0 | J31: 0
A32: IMPOSTO DEVIDO: | B32: =B29*B31 -> 0 | C32: =C29*C31 -> 0
A34: CONSOLIDAÇÃO DO MÊS
A35: Total do imposto devido: | C35: =B32+C32 -> 0 | F35: IR fonte (lei 11.033)
A36: IR Retido na fonte em day trade no mês:
A37: IR Retido na fonte em day trade nos meses anteriores: | C37: ='10.26'!C38 -> 0 | F37: Recolhido apenas se o valor mensal for maior que R$ 1
A38: IR Retido na fonte em day trade à compensar: | C38: =MAX(0,C36+C37-C32) -> 0
A39: IR Retido na fonte em swing trade no mês: | F39: Calculo do mês | I39: 0
A40: IR Retido na fonte em swing trade nos meses anteriores: | C40: ='10.26'!C41 -> 0 | F40: Recolhido no mês | I40: 0
A41: IR Retido na fonte em swing trade à compensar: | C41: =MAX(0,C39+C40-B32) -> 0 | F41: Meses anteriores | I41: 0
A42: Imposto à pagar: | C42: =MAX(0,C32-(C36+C37))+MAX(0,B32-(C39+C40)) -> 0 | F42: Compensado | I42: 0
A43: Vencimento em: | C43: =IF($C$42>=10,WORKDAY(EOMONTH(DATE(2000+VALUE(RIGHT($A$6,2)),VALUE(MID($A$6,FIND(": ",$A$6)+2,2)),1),1)+1,-1),"") | F43: À compensar até dezembro | I43: 0
A47: Operações de Fundo de Investimento imobiliário e/ou Fiagros
A49: Resultado líquido do mês: | F49: Detalhamento do IR fonte (lei 11.033)
A50: Valor negativo até o mês anterior: | B50: ='10.26'!B52 -> 0
A51: Base de cálculo do imposto: | B51: =MAX(0,B49+B50) -> 0 | F51: Recolhido apenas se o valor mensal for maior que R$ 1
A52: Prejuízo à compensar: | B52: =MIN(0,B49+B50) -> 0
A53: ALÍQUOTA DO IMPOSTO (%): | B53: 0.2 | F53: Calculo do mês | I53: 0
A54: IMPOSTO DEVIDO | B54: =B51*B53 -> 0 | F54: Recolhido no mês | I54: 0
F55: Meses anteriores | I55: 0
A56: IR Retido na fonte no mês: | F56: Compensado | I56: 0
A57: IR Retido na fonte nos meses anteriores: | B57: ='10.26'!B58 -> 0 | F57: À compensar até dezembro | I57: 0
A58: IR Retido na fonte à compensar: | B58: =MAX(0,B56+B57-B54) -> 0
A59: Imposto à pagar: | B59: =MAX(0,B54-(B56+B57)) -> 0
A60: Vencimento em: | B60: =IF($B$59>=10,WORKDAY(EOMONTH(DATE(2000+VALUE(RIGHT($A$6,2)),VALUE(MID($A$6,FIND(": ",$A$6)+2,2)),1),1)+1,-1),"")

Sheet 12.26
A6: PERÍODO DE APURAÇÃO: 12.26
A7: INVESTIDOR:
A8: CPF:
A10: OPERAÇÕES RENDA VARIÁVEL
B14: SWING TRADE | C14: DAY TRADE: | F14: Informações complementares:
A15: Mercado à vista - ações:
A16: Mercado à vista - ouro: | F16: Isenção de IR
A18: Mercado de opções: | F18: I. Referente à alienação até R$ 20 mil no mercado à vista
A19: Mercado de opções flexíveis:
A20: Mercado à termo: | G20: Alienações (Vendas) | J20: Ganho Isento
F21: Ação | G21: 0 | J21: 0
A22: Mercado futuro - dólar:
A23: Mercado futuro - índices: | F23: Ouro | G23: 0 | J23: 0
A24: Mercado futuro - juros:
A25: Mercado futuro - outros:
F26: II. Referente à ações de pequenas e médias empresas
A27: RESULTADO LÍQUIDO DO MÊS | B27: =SUM(B15:B25) -> 0 | C27: =SUM(C15:C25) -> 0
A28: Resultado negativo até o mês anterior | B28: ='11.26'!B30 -> 0 | C28: ='11.26'!C30 -> 0 | G28: Ativos isentos op. ST | J28: Ativos isentos op. DT
A29: BASE DE CÁLCULO DO IMPOSTO: | B29: =MAX(0,B27+B28) -> 0 | C29: =MAX(0,C27+C28) -> 0 | F29: Ação | G29: 0 | J29: 0
A30: Prejuízo à compensar | B30: =MIN(0,B27+B28) -> 0 | C30: =MIN(0,C27+C28) -> 0
A31: ALÍQUOTA DO IMPOSTO (%): | B31: 0.15 | C31: 0.2 | F31: Ouro | G31: 0 | J31: 0
A32: IMPOSTO DEVIDO: | B32: =B29*B31 -> 0 | C32: =C29*C31 -> 0
A34: CONSOLIDAÇÃO DO MÊS
A35: Total do imposto devido: | C35: =B32+C32 -> 0 | F35: IR fonte (lei 11.033)
A36: IR Retido na fonte em day trade no mês:
A37: IR Retido na fonte em day trade nos meses anteriores: | C37: ='11.26'!C38 -> 0 | F37: Recolhido apenas se o valor mensal for maior que R$ 1
A38: IR Retido na fonte em day trade à compensar: | C38: =MAX(0,C36+C37-C32) -> 0
A39: IR Retido na fonte em swing trade no mês: | F39: Calculo do mês | I39: 0
A40: IR Retido na fonte em swing trade nos meses anteriores: | C40: ='11.26'!C41 -> 0 | F40: Recolhido no mês | I40: 0
A41: IR Retido na fonte em swing trade à compensar: | C41: =MAX(0,C39+C40-B32) -> 0 | F41: Meses anteriores | I41: 0
A42: Imposto à pagar: | C42: =MAX(0,C32-(C36+C37))+MAX(0,B32-(C39+C40)) -> 0 | F42: Compensado | I42: 0
A43: Vencimento em: | C43: =IF($C$42>=10,WORKDAY(EOMONTH(DATE(2000+VALUE(RIGHT($A$6,2)),VALUE(MID($A$6,FIND(": ",$A$6)+2,2)),1),1)+1,-1),"") | F43: À compensar até dezembro | I43: 0
A47: Operações de Fundo de Investimento imobiliário e/ou Fiagros
A49: Resultado líquido do mês: | F49: Detalhamento do IR fonte (lei 11.033)
A50: Valor negativo até o mês anterior: | B50: ='11.26'!B52 -> 0
A51: Base de cálculo do imposto: | B51: =MAX(0,B49+B50) -> 0 | F51: Recolhido apenas se o valor mensal for maior que R$ 1
A52: Prejuízo à compensar: | B52: =MIN(0,B49+B50) -> 0
A53: ALÍQUOTA DO IMPOSTO (%): | B53: 0.2 | F53: Calculo do mês | I53: 0
A54: IMPOSTO DEVIDO | B54: =B51*B53 -> 0 | F54: Recolhido no mês | I54: 0
F55: Meses anteriores | I55: 0
A56: IR Retido na fonte no mês: | F56: Compensado | I56: 0
A57: IR Retido na fonte nos meses anteriores: | B57: ='11.26'!B58 -> 0 | F57: À compensar até dezembro | I57: 0
A58: IR Retido na fonte à compensar: | B58: =MAX(0,B56+B57-B54) -> 0
A59: Imposto à pagar: | B59: =MAX(0,B54-(B56+B57)) -> 0
A60: Vencimento em: | B60: =IF($B$59>=10,WORKDAY(EOMONTH(DATE(2000+VALUE(RIGHT($A$6,2)),VALUE(MID($A$6,FIND(": ",$A$6)+2,2)),1),1)+1,-1),"")
